{
  "users": [
    {
      "id": "d1e6",
      "name_signin": "",
      "password_name": "",
      "password_confirm_name": ""
    },
    {
      "id": "e9e5",
      "name_signin": "123",
      "password_name": "123",
      "password_confirm_name": "123"
    },
    {
      "id": "9aef",
      "name_signin": "",
      "password_name": "",
      "password_confirm_name": ""
    },
    {
      "id": "4b5a",
      "name_signin": "",
      "password_name": "",
      "password_confirm_name": ""
    },
    {
      "id": "b2c5",
      "name_signin": "nigar",
      "password_name": "123",
      "password_confirm_name": "123"
    },
    {
      "id": "9544",
      "name_signin": "admin",
      "password_name": "1",
      "password_confirm_name": "1"
    },
    {
      "id": "a77f",
      "name_signin": "Nigarcim",
      "password_name": "nigarcim",
      "password_confirm_name": "nigarcim"
    },
    {
      "id": "9dc3",
      "name_signin": "Nigarcim",
      "password_name": "nigarcim",
      "password_confirm_name": "nigarcim"
    },
    {
      "id": "8325",
      "name": "Nigar",
      "position": "mudir"
    },
    {
      "id": "c785",
      "name": "Nigar",
      "email": "nigarramazanli9@gmail.com",
      "password": "123"
    },
    {
      "id": "813e",
      "name": "Nigar",
      "email": "nigarramazanli9@gmail.com",
      "password": "123"
    },
    {
      "id": "5833",
      "name": "Nigar",
      "email": "nigarramazanli9@gmail.com",
      "password": "123"
    },
    {
      "id": "36a7",
      "name": "Nigar",
      "email": "nigarramazanli9@gmail.com",
      "password": "123"
    },
    {
      "id": "0128",
      "name": "Nigar",
      "email": "nigarramazanli9@gmail.com",
      "password": "123"
    },
    {
      "id": "5236",
      "name": "Nigar",
      "email": "nigarramazanli9@gmail.com",
      "password": "123"
    },
    {
      "id": "d146",
      "name": "Nigar",
      "email": "nigarramazanli9@gmail.com",
      "password": "123"
    },
    {
      "id": "2f4b",
      "name": "Vuqar",
      "email": "vuqar9@gmail.com",
      "password": "vuqarMuellim"
    },
    {
      "id": "c698",
      "name": "Vuqar",
      "email": "vuqar9@gmail.com",
      "password": "vuqarMuellim"
    },
    {
      "id": "c7a9",
      "name": "Vuqar",
      "email": "vuqar9@gmail.com",
      "password": "vuqarMuellim"
    },
    {
      "id": "b0bc",
      "name": "Nigar",
      "email": "nigar12344321",
      "password": "nigar12344321"
    },
    {
      "id": "9ee6",
      "name": "Nigar",
      "email": "1234",
      "password": "1234"
    },
    {
      "id": "582e",
      "name": "Nigar",
      "email": "nigarramazanli9@gmail.com",
      "password": "nigar1234"
    },
    {
      "id": "6e1b",
      "name": "",
      "email": "",
      "password": ""
    },
    {
      "id": "8875",
      "name": "",
      "email": "",
      "password": ""
    },
    {
      "id": "2d14",
      "name": "",
      "email": "",
      "password": ""
    },
    {
      "id": "671d",
      "name": "Nigar",
      "email": "nigarramazanli9@gmail.com",
      "password": "nigarsansli"
    },
    {
      "id": "2ab4",
      "name": "",
      "email": "",
      "password": ""
    },
    {
      "id": "8114",
      "name": "",
      "position": "mudir"
    },
    {
      "id": "1e1a",
      "name": "",
      "position": "muavin"
    },
    {
      "id": "0390",
      "name": "Nigar",
      "email": "nigarramazanli9@gmail.com",
      "password": "nigar1234"
    },
    {
      "id": "ebe2",
      "name": "Zur",
      "email": "nigarramazanli9@gmail.com",
      "password": "nigar1234"
    },
    {
      "id": "472c",
      "name": "Nigar",
      "email": "nigarram",
      "password": "nigar4321"
    },
    {
      "id": "3a6a",
      "name": "",
      "email": "nigarramazanli9gmail.com",
      "password": ""
    },
    {
      "id": "a1c5",
      "name": "Nigar",
      "email": "nigarramazanli9@",
      "password": "nigar1234"
    },
    {
      "id": "efbb",
      "name": "Nigar",
      "email": "nigarramazanli9@",
      "password": "nigar4321"
    },
    {
      "id": "74c9",
      "name": "Nigar",
      "email": "nigarramazanli9@gmail.com",
      "password": "nigar4321"
    },
    {
      "id": "a696",
      "name": "Nigar",
      "email": "nigarramazanli9@gmail.com",
      "password": "nigar4321"
    },
    {
      "id": "6a39",
      "name": "Nigar",
      "email": "nigarramazanli9@gmail.com",
      "password": "nigar4321"
    },
    {
      "id": "1093",
      "name": "Nigar",
      "email": "nigarramazanli9@gmail.com",
      "password": "nigar4321"
    },
    {
      "id": "bffa",
      "name": "Nigar",
      "email": "nigarramazanli9@gmail.com",
      "password": "nigar4321"
    },
    {
      "id": "2cb0",
      "name": "Nigar",
      "email": "nigarramazanli9@gmail.com",
      "password": "nigar4321"
    },
    {
      "id": "6789",
      "name": "Nigar",
      "email": "nigarramazanli9@gmail.com",
      "password": "nigar4321"
    },
    {
      "id": "6d8c",
      "name": "Nigar",
      "email": "nigarramazanli9@gmail.com",
      "password": "nigar4321"
    },
    {
      "id": "876c",
      "name": "Nigar",
      "email": "nigarramazanli9@gmail.com",
      "password": "nigar4321"
    },
    {
      "id": "8855",
      "name": "Nigar",
      "email": "nigarramazanli9@gmail.com",
      "password": "nigar4321"
    },
    {
      "id": "c4f6",
      "name": "Nigar",
      "email": "nigarramazanli9@gmail.com",
      "password": "nigar4321"
    },
    {
      "id": "12f2",
      "name": "Nigar",
      "email": "nigarramazanli9@gmail.com",
      "password": "nigar1234"
    },
    {
      "id": "812d",
      "name": "Nigar",
      "email": "nigarramazanli9@gmail",
      "password": "nigar1234"
    },
    {
      "id": "859c",
      "name": "Nigar",
      "email": "nigarramazanli9@gmail",
      "password": "nigar1234"
    },
    {
      "id": "1c78",
      "name": "Nigar",
      "email": "nigarramazanli9@gmail",
      "password": "nigar1234"
    },
    {
      "id": "c891",
      "name": "Nigar",
      "email": "nigarramazanli9@gmail.com",
      "password": "nigar1234"
    },
    {
      "id": "2513",
      "name": "Nigar",
      "email": "nigarramazanli9@gmail.com",
      "password": "nigar1234"
    },
    {
      "id": "ef7e",
      "name": "Nigar",
      "email": "example@example.com",
      "password": "nigar1234"
    },
    {
      "id": "5c75",
      "name": "Nigar",
      "email": "example@example.com",
      "password": "nigar1234"
    },
    {
      "id": "2495",
      "name": "Nigar",
      "email": "example@example.com",
      "password": "nigar1234"
    },
    {
      "id": "c715",
      "name": "Nigar",
      "email": "example@example.com",
      "password": "nigar1234"
    },
    {
      "id": "ac1e",
      "name": "Nigar",
      "email": "example@example.com",
      "password": "nigar1234"
    },
    {
      "id": "9eeb",
      "name": "Nigar",
      "email": "nigarramazanli9@gmail.com",
      "password": "nigar1234"
    },
    {
      "id": "bbae",
      "name": "",
      "email": "user.name@subdomain.example.com",
      "password": ""
    },
    {
      "id": "039c",
      "name": "Nigar",
      "email": "user.name@subdomain.example.com",
      "password": "nigar1234"
    },
    {
      "id": "62f0",
      "name": "Nigar",
      "email": "nigarramazanli9@gmail.com",
      "password": "nigar4321"
    },
    {
      "id": "fe1a",
      "name": "Nigar",
      "email": "nigarramazanli9@gmail.com",
      "password": "nigar4321"
    },
    {
      "id": "09bd",
      "email": "nigarramazanli9@gmail.com",
      "password": "nigarR4$mail@gmail$"
    },
    {
      "id": "c43e",
      "name": "Nigar",
      "position": "mudir"
    },
    {
      "id": "e915",
      "name": "Nigar",
      "position": "mudir"
    },
    {
      "id": "fc13",
      "name": "Nigar",
      "position": "mudir"
    },
    {
      "id": "79c3",
      "name": "Nigar",
      "position": "mudir"
    },
    {
      "id": "1849",
      "name": "Nigar",
      "position": "mudir"
    },
    {
      "id": "3581",
      "name": "Nigar",
      "position": "mudir"
    },
    {
      "id": "204f",
      "name": "Nigar",
      "position": "proqramist"
    },
    {
      "id": "bd4f",
      "name": "Nigar",
      "position": "proqramist",
      "number": "050 840 26 18"
    },
    {
      "id": "d2d5",
      "name": "Nigar",
      "position": "mudir",
      "number": "508402618"
    },
    {
      "id": "97d4",
      "name": "Nigar",
      "position": "mudir",
      "number": "508402618"
    },
    {
      "id": "344c",
      "name": "Nigar",
      "position": "proqramist",
      "number": "0508442628"
    },
    {
      "id": "8086",
      "name": "Nigar",
      "position": "mudir",
      "number": "050 840 26 18"
    },
    {
      "id": "5473",
      "name": "Nigar",
      "position": "mudir",
      "number": "050 840 26 18"
    },
    {
      "id": "943a",
      "name": "Nigar",
      "position": "mudir",
      "number": "0508402618"
    },
    {
      "id": "e6bf",
      "name": "Nigar",
      "position": "mudir",
      "number": "0508402618"
    },
    {
      "id": "0388",
      "name": "Nigar",
      "position": "mudir",
      "number": "0508402618"
    },
    {
      "id": "477f",
      "name": "",
      "position": "mudir",
      "number": "0508402618"
    },
    {
      "id": "f24f",
      "name": "Xezan",
      "position": "mudir",
      "number": "0508402618"
    },
    {
      "id": "d7dd",
      "name": "Xezan",
      "number": "0508402618"
    },
    {
      "id": "cb0b",
      "name": "Nigar",
      "number": "0508402618",
      "surname": "Ramazanli",
      "username": "NigarRamazanl9",
      "email": "nigarramazanli9@gmail.com",
      "relativeName": "Zuma",
      "relativeNumber": "050 541 06 67",
      "relationship": "ana",
      "finCode": "5KS7YLM",
      "seriyaCode": "eqe27ete7t287e",
      "address": "Sumqayit seheri",
      "addressLiving": "Baki seheri",
      "userImage": "",
      "vesiqeImage": "",
      "filial": "28 May",
      "baslamaTarixi": "2024-08-01",
      "terkEtmeTarixi": "2025-06-26",
      "userPosition": "mudir",
      "educationLevel": "Ali",
      "isNomresi": "050 341 44 43",
      "isdenCixmaSebebi": "sebeb",
      "note": "sebeb"
    },
    {
      "id": "4d29",
      "name": "Nigar",
      "number": "0508402618",
      "surname": "Ramazanli",
      "username": "sbdhbdbs",
      "email": "adfdfadabf",
      "relativeName": "ana",
      "relativeNumber": "050 840 26 18",
      "relationship": "ana",
      "finCode": "tfytf7d",
      "seriyaCode": "f76fr5frtfd7667678677676676767",
      "address": "Sumqayit",
      "addressLiving": "Sumqayit",
      "userImage": "C:\\fakepath\\ugur.jpg",
      "vesiqeImage": "C:\\fakepath\\icons8-web-48.png",
      "filial": "28 May",
      "baslamaTarixi": "2024-08-10",
      "terkEtmeTarixi": "2027-06-26",
      "userPosition": "mudir",
      "educationLevel": "Ali",
      "isNomresi": "050 840 26 18",
      "isdenCixmaSebebi": "sebeb",
      "note": "rgryet"
    },
    {
      "id": "0d2c",
      "name": "Nigar",
      "number": "0508402618",
      "surname": "hbugdcis",
      "username": "cbdgfwf",
      "email": "nhbdgefeda",
      "relativeName": "A",
      "relativeNumber": "050 840 26 18",
      "relationship": "ana",
      "finCode": "gstw76fddd777777",
      "seriyaCode": "wenfwefbwed",
      "address": "jncdefweif",
      "addressLiving": "njebfewf",
      "filial": "Ağ Şəhər",
      "baslamaTarixi": "",
      "terkEtmeTarixi": "",
      "userPosition": "mudir",
      "educationLevel": "Ali",
      "isNomresi": "050 840 26 18",
      "isdenCixmaSebebi": "",
      "note": ""
    },
    {
      "id": "20b5",
      "name": "Nigar",
      "number": "0508402618",
      "surname": "",
      "username": "",
      "email": "",
      "relativeName": "A",
      "relativeNumber": "050 840 26 18",
      "relationship": "ana",
      "finCode": "",
      "seriyaCode": "",
      "address": "",
      "addressLiving": "",
      "userImage": "blob:null/5d7a6d21-07ff-493f-a354-c441395fde05",
      "vesiqeImage": "blob:null/5d7a6d21-07ff-493f-a354-c441395fde05",
      "filial": "Ağ Şəhər",
      "baslamaTarixi": "",
      "terkEtmeTarixi": "",
      "userPosition": "mudir",
      "educationLevel": "Ali",
      "isNomresi": "050 840 26 18",
      "isdenCixmaSebebi": "",
      "note": ""
    },
    {
      "id": "30f4",
      "name": "",
      "number": "0508402618",
      "surname": "",
      "username": "",
      "email": "",
      "relativeName": "",
      "relativeNumber": "050 840 26 18",
      "relationship": "ana",
      "finCode": "",
      "seriyaCode": "",
      "address": "",
      "addressLiving": "",
      "userImage": "blob:null/6a4c29af-79b5-4b5b-a460-38ba097af2f5",
      "vesiqeImage": "blob:null/6a4c29af-79b5-4b5b-a460-38ba097af2f5",
      "filial": "Ağ Şəhər",
      "baslamaTarixi": "",
      "terkEtmeTarixi": "",
      "userPosition": "mudir",
      "educationLevel": "Ali",
      "isNomresi": "050 840 26 18",
      "isdenCixmaSebebi": "",
      "note": ""
    },
    {
      "id": "d581",
      "name": "",
      "number": "0508402618",
      "surname": "",
      "username": "",
      "email": "",
      "relativeName": "",
      "relativeNumber": "050 840 26 18",
      "relationship": "ana",
      "finCode": "",
      "seriyaCode": "",
      "address": "",
      "addressLiving": "",
      "userImage": "file:///C:/Users/ASUS/real-estate/public/userProfilImage1.jpg",
      "vesiqeImage": "file:///C:/Users/ASUS/real-estate/public/userProfilImage1.jpg",
      "filial": "Ağ Şəhər",
      "baslamaTarixi": "",
      "terkEtmeTarixi": "",
      "userPosition": "mudir",
      "educationLevel": "Ali",
      "isNomresi": "050 840 26 18",
      "isdenCixmaSebebi": "",
      "note": ""
    },
    {
      "id": "af8e",
      "name": "",
      "number": "0508402618",
      "surname": "",
      "username": "",
      "email": "",
      "relativeName": "",
      "relativeNumber": "050 840 26 18",
      "relationship": "ana",
      "finCode": "",
      "seriyaCode": "",
      "address": "",
      "addressLiving": "",
      "userImage": "blob:null/14725555-56b7-49ef-b1c6-79ef4acb2798",
      "vesiqeImage": "blob:null/14725555-56b7-49ef-b1c6-79ef4acb2798",
      "filial": "Ağ Şəhər",
      "baslamaTarixi": "",
      "terkEtmeTarixi": "",
      "userPosition": "mudir",
      "educationLevel": "Ali",
      "isNomresi": "050 840 26 18",
      "isdenCixmaSebebi": "",
      "note": ""
    },
    {
      "id": "09e1",
      "name": "",
      "number": "0508402618",
      "surname": "",
      "username": "",
      "email": "",
      "relativeName": "",
      "relativeNumber": "050 840 26 18",
      "relationship": "ana",
      "finCode": "",
      "seriyaCode": "",
      "address": "",
      "addressLiving": "",
      "userImage": "file:///C:/Users/ASUS/real-estate/public/userProfilImage1.jpg",
      "vesiqeImage": "file:///C:/Users/ASUS/real-estate/public/userProfilImage1.jpg",
      "filial": "Ağ Şəhər",
      "baslamaTarixi": "",
      "terkEtmeTarixi": "",
      "userPosition": "mudir",
      "educationLevel": "Ali",
      "isNomresi": "050 840 26 18",
      "isdenCixmaSebebi": "",
      "note": ""
    },
    {
      "id": "093e",
      "name": "",
      "number": "0508402618",
      "surname": "",
      "username": "",
      "email": "",
      "relativeName": "",
      "relativeNumber": "050 840 26 18",
      "relationship": "ana",
      "finCode": "",
      "seriyaCode": "",
      "address": "",
      "addressLiving": "",
      "userImage": "blob:null/2e30e831-268b-4c16-addb-8c326e3e67b3",
      "vesiqeImage": "blob:null/2e30e831-268b-4c16-addb-8c326e3e67b3",
      "filial": "28 May",
      "baslamaTarixi": "2024-09-10",
      "terkEtmeTarixi": "2027-07-26",
      "userPosition": "mudir",
      "educationLevel": "Ali",
      "isNomresi": "050 840 26 18",
      "isdenCixmaSebebi": "",
      "note": ""
    },
    {
      "id": "fe18",
      "name": "",
      "number": "0508402618",
      "surname": "",
      "username": "",
      "email": "",
      "relativeName": "",
      "relativeNumber": "0508402618",
      "relationship": "ana",
      "finCode": "",
      "seriyaCode": "",
      "address": "",
      "addressLiving": "",
      "userImage": "file:///C:/Users/ASUS/real-estate/public/userProfilImage1.jpg",
      "vesiqeImage": "file:///C:/Users/ASUS/real-estate/public/userProfilImage1.jpg",
      "filial": "Ağ Şəhər",
      "baslamaTarixi": "",
      "terkEtmeTarixi": "",
      "userPosition": "mudir",
      "educationLevel": "Ali",
      "isNomresi": "0508402618",
      "isdenCixmaSebebi": "",
      "note": ""
    },
    {
      "id": "369e",
      "name": "Nigar",
      "number": "0508402618",
      "surname": "Ramazanli",
      "username": "NigarRamazanli",
      "email": "nigarramazanli9@gmail.com",
      "relativeName": "yedyeyt",
      "relativeNumber": "0508402618",
      "relationship": "ana",
      "finCode": "grfggsrf",
      "seriyaCode": "bhgfhrrss",
      "address": "bhdrfghfs",
      "addressLiving": "grfgfhsrfg",
      "userImage": "blob:null/1a66f201-64ff-4f39-a957-bbef0bd98d09",
      "vesiqeImage": "blob:null/1a66f201-64ff-4f39-a957-bbef0bd98d09",
      "filial": "28 May",
      "baslamaTarixi": "2024-08-08",
      "terkEtmeTarixi": "2024-08-03",
      "userPosition": "proqramist",
      "educationLevel": "Ali",
      "isNomresi": "0508402618",
      "isdenCixmaSebebi": "xarice kocmek, isden cox pul verib saxlamaq isteseler de kocmek isteyirem/",
      "note": "xrxskrdx"
    },
    {
      "id": "8117",
      "name": "",
      "email": "",
      "password": ""
    },
    {
      "id": "2284",
      "name": "",
      "email": "",
      "password": ""
    },
    {
      "id": "f1e7",
      "name": "Nigar",
      "email": "nigarramazanli9@gmail.com",
      "password": "nigar1234"
    },
    {
      "id": "ff38",
      "name": "Nigar",
      "email": "nigarramazanli9@gmail.com",
      "password": "nigar1234"
    },
    {
      "id": "b23b",
      "name": "Nigar",
      "email": "11",
      "password": "11"
    },
    {
      "id": "93ce",
      "name": "Nigar",
      "email": "11",
      "password": "11"
    },
    {
      "id": "8673",
      "name": "",
      "email": "",
      "password": ""
    },
    {
      "id": "290f",
      "name": "",
      "email": "",
      "password": ""
    },
    {
      "id": "5934",
      "name": "",
      "email": "",
      "password": ""
    },
    {
      "id": "ef6e",
      "name": "",
      "email": "",
      "password": ""
    },
    {
      "id": "0003",
      "name": "",
      "email": "",
      "password": ""
    },
    {
      "id": "8cc1",
      "name": "",
      "email": "",
      "password": ""
    },
    {
      "id": "cf13",
      "name": "Nigar",
      "email": "nigarramazanli9@gmail.com",
      "password": "nigar1234"
    },
    {
      "id": "5c36",
      "name": "Nigar",
      "email": "nigarramazanli9@gmail.com",
      "password": "nigar1234"
    },
    {
      "id": "6c1a",
      "name": "Nigar",
      "email": "nigarram.com",
      "password": "nigar1234"
    },
    {
      "id": "070f",
      "name": "Nigar",
      "email": "nigarram.com",
      "password": "nigar1234"
    },
    {
      "id": "3df8",
      "name": "",
      "email": "",
      "password": ""
    },
    {
      "id": "563c",
      "name": "",
      "email": "",
      "password": ""
    },
    {
      "id": "f1b1",
      "name": "Nigar",
      "email": "nigarramazanli9@gmail.com",
      "password": "nigar1234"
    },
    {
      "id": "e3b0",
      "name": "Nigar",
      "email": "nigarramazanli9@gmail.com",
      "password": "nigar1234"
    }
  ],
  "users_LogIn": [
    {
      "id": "c03e",
      "filialName": "",
      "phone": "050 840 26 18",
      "note": "28 May"
    },
    {
      "id": "cf01",
      "filialName": "28May",
      "phone": "050 840 26 18",
      "note": "28 May"
    },
    {
      "id": "1678",
      "filialName": "28May",
      "phone": "050 8402618",
      "note": "28 May"
    },
    {
      "id": "e09c",
      "filialName": "28May",
      "phone": "050 8402618",
      "note": "28 May"
    },
    {
      "id": "39d5",
      "filialName": "",
      "phone": "050 8402618",
      "note": ""
    },
    {
      "id": "3d0d",
      "filialName": "28May",
      "phone": "099 840 26 18",
      "note": "28 May"
    },
    {
      "id": "fc20",
      "filialName": "",
      "phone": "077 840 26 18",
      "note": ""
    },
    {
      "id": "0cbb",
      "filialName": "28May",
      "phone": "0508402618",
      "note": "EYD"
    },
    {
      "id": "6a84",
      "filialName": "",
      "phone": "0509997777",
      "note": "EYD"
    },
    {
      "id": "06b7",
      "filialName": "",
      "phone": "",
      "note": ""
    },
    {
      "id": "2e1b",
      "filialName": "Elmlər",
      "phone": "0508402618",
      "note": "28 May"
    },
    {
      "id": "0f3f",
      "filialName": "",
      "phone": "",
      "note": ""
    },
    {
      "id": "f728",
      "filialName": "",
      "phone": "",
      "note": ""
    },
    {
      "id": "0b0b",
      "filialName": "",
      "phone": "",
      "note": ""
    },
    {
      "id": "8dfb",
      "filialName": "Elmlər",
      "phone": "0508402618",
      "note": "28 May"
    },
    {
      "id": "ed7f",
      "filialName": "",
      "phone": "",
      "note": ""
    },
    {
      "id": "7090",
      "filialName": "",
      "phone": "",
      "note": ""
    },
    {
      "id": "377a",
      "filialName": "",
      "phone": "",
      "note": ""
    }
  ]
}